MANIFEST.in
README.rest
setup.py
goristock.egg-info/PKG-INFO
goristock.egg-info/SOURCES.txt
goristock.egg-info/dependency_links.txt
goristock.egg-info/requires.txt
goristock.egg-info/top_level.txt
grs/BSR.py
grs/__init__.py
grs/all_portf.py
grs/cttwt.py
grs/gnews.py
grs/goapi.py
grs/goristock.py
grs/industry_code.csv
grs/mobileapi.py
grs/opendate.csv
grs/realtime.py
grs/stock_no.csv
grs/timeser.py
grs/twseno.py
grs/twseopen.py