Metadata-Version: 1.0
Name: goristock
Version: 0.5
Summary: 台灣股市分析機器人
Home-page: https://github.com/toomore/goristock
Author: Toomore Chiang
Author-email: toomore0929@gmail.com
License: MIT
Platform: UNKNOWN
Classifier: Development Status :: 4 - Beta
Classifier: Environment :: Console
Classifier: Environment :: Web Environment
Classifier: Intended Audience :: End Users/Desktop
Classifier: Intended Audience :: Financial and Insurance Industry
Classifier: Intended Audience :: Developers
Classifier: License :: OSI Approved :: MIT License
Classifier: Natural Language :: Chinese (Traditional)
Classifier: Programming Language :: Python
Classifier: Programming Language :: Python :: 2.6
Classifier: Topic :: Office/Business :: Financial :: Investment
